capture/__init__.py
capture/capture.py
capture/stop_words.py
discosg/__init__.py
discosg/dataset_utils.py
discosg/eval_utils.py
discosg/log_utils.py
discosg/parse_utils.py
discosg/triple_utils.py
discosg/utils.py
discosg/evaluation/__init__.py
discosg/evaluation/evaluator.py
discosg/evaluation/set_match_evaluation.py
discosg/evaluation/soft_spice_evaluation.py
discosg/evaluation/spice_evaluation.py
discosg/evaluation/synonym_dictionary.py
discosg/parser/DualTaskSceneGraphParser.py
discosg/parser/__init__.py
discosg_arch/T5ForDualTask.py
discosg_arch/__init__.py
discosg-0.0.5.dist-info/LICENSE
discosg-0.0.5.dist-info/METADATA
discosg-0.0.5.dist-info/WHEEL
discosg-0.0.5.dist-info/top_level.txt
discosg-0.0.5.dist-info/RECORD
