Metadata-Version: 2.1
Name: discosg
Version: 0.0.5
Summary: A package for discourse-level scene graph parsing and evaluation.
Home-page: https://github.com/ShaoqLin/DiscoSG
Author: Shaoqing Lin, Zhuang Li
Author-email: sqlinn@whu.edu.cn
Classifier: Development Status :: 3 - Alpha
Classifier: Intended Audience :: Developers
Classifier: License :: OSI Approved :: MIT License
Classifier: Programming Language :: Python :: 3
Classifier: Programming Language :: Python :: 3.10
Classifier: Programming Language :: Python :: 3.11
Classifier: Programming Language :: Python :: 3.12
Classifier: Operating System :: OS Independent
Requires-Python: >=3.8.0
License-File: LICENSE
Requires-Dist: torch<=2.6.0
Requires-Dist: transformers
Requires-Dist: tqdm
Requires-Dist: nltk
Requires-Dist: peft
Requires-Dist: huggingface-hub
